{
  "main": {
    "id": "7bee563fc6172764",
    "type": "split",
    "children": [
      {
        "id": "485d7c5091160ad2",
        "type": "tabs",
        "children": [
          {
            "id": "35b4283909d4e5a9",
            "type": "leaf",
            "state": {
              "type": "markdown",
              "state": {
                "file": "University/CS/Computer Graphics/Graphics Pipeline.md",
                "mode": "source",
                "source": false
              }
            }
          }
        ]
      }
    ],
    "direction": "vertical"
  },
  "left": {
    "id": "b148a175122ec89b",
    "type": "split",
    "children": [
      {
        "id": "42114bdc0d0fc3a2",
        "type": "tabs",
        "children": [
          {
            "id": "9797157a9528fe3d",
            "type": "leaf",
            "state": {
              "type": "file-explorer",
              "state": {
                "sortOrder": "alphabetical"
              }
            }
          },
          {
            "id": "43d5181e56252d23",
            "type": "leaf",
            "state": {
              "type": "search",
              "state": {
                "query": "",
                "matchingCase": false,
                "explainSearch": false,
                "collapseAll": false,
                "extraContext": false,
                "sortOrder": "alphabetical"
              }
            }
          },
          {
            "id": "f9d9e48b02abe40d",
            "type": "leaf",
            "state": {
              "type": "bookmarks",
              "state": {}
            }
          }
        ]
      }
    ],
    "direction": "horizontal",
    "width": 300
  },
  "right": {
    "id": "d7a2831e1989883b",
    "type": "split",
    "children": [
      {
        "id": "7d0d3f1090009ccb",
        "type": "tabs",
        "children": [
          {
            "id": "7df5f6e7dde1cc63",
            "type": "leaf",
            "state": {
              "type": "backlink",
              "state": {
                "file": "University/CS/Computer Graphics/Graphics Pipeline.md",
                "collapseAll": false,
                "extraContext": false,
                "sortOrder": "alphabetical",
                "showSearch": false,
                "searchQuery": "",
                "backlinkCollapsed": false,
                "unlinkedCollapsed": true
              }
            }
          },
          {
            "id": "31573729836a133c",
            "type": "leaf",
            "state": {
              "type": "outgoing-link",
              "state": {
                "file": "University/CS/Computer Graphics/Graphics Pipeline.md",
                "linksCollapsed": false,
                "unlinkedCollapsed": true
              }
            }
          },
          {
            "id": "8db2c27c27e7871c",
            "type": "leaf",
            "state": {
              "type": "tag",
              "state": {
                "sortOrder": "frequency",
                "useHierarchy": true
              }
            }
          },
          {
            "id": "bf8897b6797a5e0f",
            "type": "leaf",
            "state": {
              "type": "all-properties",
              "state": {
                "sortOrder": "frequency",
                "showSearch": false,
                "searchQuery": ""
              }
            }
          },
          {
            "id": "6308bd2e4dbb4bd9",
            "type": "leaf",
            "state": {
              "type": "outline",
              "state": {
                "file": "University/CS/Computer Graphics/Graphics Pipeline.md"
              }
            }
          }
        ]
      }
    ],
    "direction": "horizontal",
    "width": 300,
    "collapsed": true
  },
  "left-ribbon": {
    "hiddenItems": {
      "table-editor-obsidian:Advanced Tables Toolbar": false,
      "switcher:Open quick switcher": false,
      "graph:Open graph view": false,
      "canvas:Create new canvas": false,
      "daily-notes:Open today's daily note": false,
      "templates:Insert template": false,
      "command-palette:Open command palette": false
    }
  },
  "active": "35b4283909d4e5a9",
  "lastOpenFiles": [
    "University/CS/Computer Graphics/Images.md",
    "University/CS/Computer Graphics/Math.md",
    "Pasted image 20240917103417.png",
    "University/CS/Computer Graphics/Graphics Pipeline.md",
    "University/CS/OS/Context-Switching, User-level Threading.md",
    "University/CS/OS/Disks.md"
  ]
}